griptapecli/__init__.py
griptapecli/commands/__init__.py
griptapecli/commands/skatepark.py
griptapecli/core/__init__.py
griptapecli/core/models.py
griptapecli/core/skatepark.py
griptapecli/core/state.py
griptapecli/main.py
griptape_cli-0.6.0.dist-info/LICENSE
griptape_cli-0.6.0.dist-info/METADATA
griptape_cli-0.6.0.dist-info/WHEEL
griptape_cli-0.6.0.dist-info/entry_points.txt
griptape_cli-0.6.0.dist-info/RECORD
