Metadata-Version: 2.1
Name: griptape-cli
Version: 0.6.0
Summary: CLI for the Griptape Framework and Cloud
Home-page: https://github.com/griptape-ai/griptape-cli
License: Apache 2.0
Author: Griptape
Author-email: hello@griptape.ai
Requires-Python: >=3.11.0,<3.12.0
Classifier: License :: Other/Proprietary License
Classifier: Programming Language :: Python :: 3
Classifier: Programming Language :: Python :: 3.11
Requires-Dist: attrs (>=23.1.0,<24.0.0)
Requires-Dist: click (>=8.1.3,<9.0.0)
Requires-Dist: fastapi (>=0.110.1,<0.111.0)
Requires-Dist: griptape (>=0.25.0,<0.26.0)
Requires-Dist: python-dotenv (>=1.0.1,<2.0.0)
Requires-Dist: uvicorn[standard] (>=0.29.0,<0.30.0)
Project-URL: Repository, https://github.com/griptape-ai/griptape-cli
